ecc/README.md
ecc/__init__.py
ecc/curve.py
ecc/ecdh.py
ecc/ecdsa.py
ecc/field.py
ecc/keys.py
ecc/point.py
ecc/curves/__init__.py
ecc/curves/secp256k1.py
eccrypto-0.2.0.dist-info/METADATA
eccrypto-0.2.0.dist-info/WHEEL
eccrypto-0.2.0.dist-info/licenses/LICENSE
eccrypto-0.2.0.dist-info/RECORD
