Metadata-Version: 2.4
Name: eccrypto
Version: 0.2.0
Summary: Pure Python library for Elliptic Curve Cryptography (ECC) — built from scratch with clarity and educational readability in mind
Project-URL: Homepage, https://github.com/drtoxic69/ECC
Project-URL: Repository, https://github.com/drtoxic69/ECC
Project-URL: Issues, https://github.com/drtoxic69/ECC/issues
Project-URL: Documentation, https://github.com/drtoxic69/ECC#readme
Project-URL: Source Code, https://github.com/drtoxic69/ECC
Project-URL: Bug Reports, https://github.com/drtoxic69/ECC/issues
Project-URL: Changelog, https://github.com/drtoxic69/ECC/releases
Author-email: Shivakumar <shivakumarjagadish12@gmail.com>
License: GPL-3.0
License-File: LICENSE
Keywords: crypto,cryptography,digital-signatures,ecc,ecdsa,elliptic-curve,secp256k1,security
Classifier: Development Status :: 5 - Production/Stable
Classifier: Intended Audience :: Developers
Classifier: Intended Audience :: Education
Classifier: Intended Audience :: Science/Research
Classifier: License :: OSI Approved :: GNU General Public License v3 (GPLv3)
Classifier: Operating System :: OS Independent
Classifier: Programming Language :: Python :: 3
Classifier: Programming Language :: Python :: 3.10
Classifier: Programming Language :: Python :: 3.11
Classifier: Programming Language :: Python :: 3.12
Classifier: Programming Language :: Python :: 3.13
Classifier: Topic :: Education
Classifier: Topic :: Security :: Cryptography
Classifier: Topic :: Software Development :: Libraries :: Python Modules
Classifier: Typing :: Typed
Requires-Python: >=3.10
